pywindsorai/__init__.py
pywindsorai/client.py
pywindsorai/enums.py
test/__init__.py
test/tests.py
pywindsorai-1.0.6.dist-info/METADATA
pywindsorai-1.0.6.dist-info/WHEEL
pywindsorai-1.0.6.dist-info/top_level.txt
pywindsorai-1.0.6.dist-info/RECORD
